winzy_days_till/__init__.py
winzy_days_till-0.1.2.dist-info/LICENSE
winzy_days_till-0.1.2.dist-info/METADATA
winzy_days_till-0.1.2.dist-info/WHEEL
winzy_days_till-0.1.2.dist-info/entry_points.txt
winzy_days_till-0.1.2.dist-info/top_level.txt
winzy_days_till-0.1.2.dist-info/RECORD
