Metadata-Version: 2.1
Name: winzy-days-till
Version: 0.1.2
Summary: Gives days remaining till the given date
Author: Sukhbinder Singh
License: Apache-2.0
Project-URL: Homepage, https://github.com/sukhbinder/winzy-days-till
Project-URL: Changelog, https://github.com/sukhbinder/winzy-days-till/releases
Project-URL: Issues, https://github.com/sukhbinder/winzy-days-till/issues
Project-URL: CI, https://github.com/sukhbinder/winzy-days-till/actions
Classifier: License :: OSI Approved :: Apache Software License
License-File: LICENSE
Requires-Dist: winzy
Requires-Dist: python-dateutil
Requires-Dist: winsay ; platform_system == "Windows"
Provides-Extra: test
Requires-Dist: pytest ; extra == 'test'
